ragorez/__init__.py
ragorez/scrapper/__init__.py
ragorez/scrapper/pipeline.py
ragorez/scrapper/etl/__init__.py
ragorez/scrapper/etl/extraction.py
ragorez/scrapper/etl/load.py
ragorez/scrapper/etl/transformation.py
ragorez_scrapper-0.1.3.dist-info/METADATA
ragorez_scrapper-0.1.3.dist-info/WHEEL
ragorez_scrapper-0.1.3.dist-info/top_level.txt
ragorez_scrapper-0.1.3.dist-info/RECORD
